rdd/__init__.py
rdd/functions.py
rdd/test.py
rdd-0.0.1.dist-info/LICENSE
rdd-0.0.1.dist-info/METADATA
rdd-0.0.1.dist-info/WHEEL
rdd-0.0.1.dist-info/top_level.txt
rdd-0.0.1.dist-info/RECORD
