Metadata-Version: 2.1
Name: rdd
Version: 0.0.1
Summary: Tools to implement regression discontinuity designs in Python.
Home-page: https://github.com/evan-magnusson/rdd
Author: Evan Magnusson
Author-email: evan.magnusson@alumni.stanford.edu
License: MIT
Platform: UNKNOWN
Classifier: Programming Language :: Python :: 3
Classifier: License :: OSI Approved :: MIT License
Requires-Dist: pandas
Requires-Dist: numpy
Requires-Dist: statsmodels
